README.rst
setup.py
panorama/__init__.py
panorama/panorama.py
panorama.egg-info/PKG-INFO
panorama.egg-info/SOURCES.txt
panorama.egg-info/dependency_links.txt
panorama.egg-info/entry_points.txt
panorama.egg-info/requires.txt
panorama.egg-info/top_level.txt