Metadata-Version: 1.1
Name: panorama
Version: 0.5.0
Summary: Create panorama in one run. Uses hugin for the real work.
Home-page: https://github.com/guettli/panorama
Author: Thomas Guettler
Author-email: guettliml.panorama@thomas-guettler.de
License: Apache Software License
Platform: UNKNOWN
Classifier: Programming Language :: Python :: 2
